dacapo/__init__.py
dacapo/apply.py
dacapo/cli.py
dacapo/options.py
dacapo/plot.py
dacapo/predict.py
dacapo/predict_local.py
dacapo/tmp.py
dacapo/train.py
dacapo/validate.py
dacapo/blockwise/__init__.py
dacapo/blockwise/argmax_worker.py
dacapo/blockwise/blockwise_task.py
dacapo/blockwise/empanada_function.py
dacapo/blockwise/predict_worker.py
dacapo/blockwise/relabel_worker.py
dacapo/blockwise/scheduler.py
dacapo/blockwise/segment_worker.py
dacapo/blockwise/threshold_worker.py
dacapo/blockwise/watershed_function.py
dacapo/compute_context/__init__.py
dacapo/compute_context/bsub.py
dacapo/compute_context/compute_context.py
dacapo/compute_context/local_torch.py
dacapo/experiments/__init__.py
dacapo/experiments/model.py
dacapo/experiments/run.py
dacapo/experiments/run_config.py
dacapo/experiments/training_iteration_stats.py
dacapo/experiments/training_stats.py
dacapo/experiments/validation_iteration_scores.py
dacapo/experiments/validation_scores.py
dacapo/experiments/architectures/__init__.py
dacapo/experiments/architectures/architecture.py
dacapo/experiments/architectures/architecture_config.py
dacapo/experiments/architectures/cnnectome_unet.py
dacapo/experiments/architectures/cnnectome_unet_config.py
dacapo/experiments/architectures/dummy_architecture.py
dacapo/experiments/architectures/dummy_architecture_config.py
dacapo/experiments/arraytypes/__init__.py
dacapo/experiments/arraytypes/annotations.py
dacapo/experiments/arraytypes/arraytype.py
dacapo/experiments/arraytypes/binary.py
dacapo/experiments/arraytypes/distances.py
dacapo/experiments/arraytypes/embedding.py
dacapo/experiments/arraytypes/intensities.py
dacapo/experiments/arraytypes/mask.py
dacapo/experiments/arraytypes/probabilities.py
dacapo/experiments/datasplits/__init__.py
dacapo/experiments/datasplits/datasplit.py
dacapo/experiments/datasplits/datasplit_config.py
dacapo/experiments/datasplits/datasplit_generator.py
dacapo/experiments/datasplits/dummy_datasplit.py
dacapo_ml-0.3.5.dist-info/METADATA
dacapo_ml-0.3.5.dist-info/WHEEL
dacapo_ml-0.3.5.dist-info/entry_points.txt
dacapo_ml-0.3.5.dist-info/licenses/LICENSE
dacapo_ml-0.3.5.dist-info/RECORD
