Metadata-Version: 2.3
Name: dacapo-ml
Version: 0.3.5
Summary: Framework for deployment of volumetric machine learning models, and easy composition of training jobs.
Project-URL: homepage, https://github.io/janelia-cellmap/dacapo
Project-URL: repository, https://github.com/janelia-cellmap/dacapo
Author-email: Will Patton <pattonw@janelia.hhmi.org>, Jeff Rhoades <rhoadesj@hhmi.org>, Marwan Zouinkhi <zouinkhim@hhmi.org>, Jan Funke <funkej@janelia.hhmi.org>
Classifier: Development Status :: 3 - Alpha
Classifier: License :: OSI Approved :: BSD License
Classifier: Natural Language :: English
Classifier: Programming Language :: Python :: 3
Classifier: Programming Language :: Python :: 3.10
Classifier: Programming Language :: Python :: 3.11
Classifier: Typing :: Typed
Requires-Python: >=3.10
Requires-Dist: attrs
Requires-Dist: bokeh
Requires-Dist: boto3
Requires-Dist: cattrs
Requires-Dist: cellmap-models
Requires-Dist: click
Requires-Dist: daisy
Requires-Dist: fibsem-tools<=6.3,>=6.0
Requires-Dist: funlib-geometry>=0.2
Requires-Dist: funlib-math>=0.1
Requires-Dist: funlib-persistence>=0.5.3
Requires-Dist: gunpowder>=1.4
Requires-Dist: lazy-property
Requires-Dist: lsds
Requires-Dist: matplotlib
Requires-Dist: mwatershed>=0.1
Requires-Dist: neuroglancer
Requires-Dist: numpy-indexed
Requires-Dist: numpy-indexed>=0.3.7
Requires-Dist: numpy>=1.22.4
Requires-Dist: pymongo
Requires-Dist: pyyaml
Requires-Dist: scipy
Requires-Dist: simpleitk
Requires-Dist: torch
Requires-Dist: tqdm
Requires-Dist: universal-pathlib<1.0.0,>=0.2.2
Requires-Dist: upath
Requires-Dist: xarray
Requires-Dist: zarr
Provides-Extra: all
Requires-Dist: black; extra == 'all'
Requires-Dist: cellmap-models; extra == 'all'
Requires-Dist: empanada-napari; extra == 'all'
Requires-Dist: ipykernel; extra == 'all'
Requires-Dist: ipython; extra == 'all'
Requires-Dist: jupyter; extra == 'all'
Requires-Dist: jupytext; extra == 'all'
Requires-Dist: matplotlib; extra == 'all'
Requires-Dist: mypy; extra == 'all'
Requires-Dist: myst-nb; extra == 'all'
Requires-Dist: myst-parser; extra == 'all'
Requires-Dist: nbsphinx; extra == 'all'
Requires-Dist: pdbpp; extra == 'all'
Requires-Dist: pooch; extra == 'all'
Requires-Dist: pre-commit; extra == 'all'
Requires-Dist: pyqt5; extra == 'all'
Requires-Dist: pytest; extra == 'all'
Requires-Dist: pytest-cov; extra == 'all'
Requires-Dist: pytest-lazy-fixtures; extra == 'all'
Requires-Dist: rich; extra == 'all'
Requires-Dist: ruff; extra == 'all'
Requires-Dist: sphinx; extra == 'all'
Requires-Dist: sphinx-autoapi; extra == 'all'
Requires-Dist: sphinx-autodoc-typehints; extra == 'all'
Requires-Dist: sphinx-click; extra == 'all'
Requires-Dist: sphinx-rtd-theme; extra == 'all'
Provides-Extra: dev
Requires-Dist: black; extra == 'dev'
Requires-Dist: mypy; extra == 'dev'
Requires-Dist: pdbpp; extra == 'dev'
Requires-Dist: pre-commit; extra == 'dev'
Requires-Dist: rich; extra == 'dev'
Requires-Dist: ruff; extra == 'dev'
Provides-Extra: docs
Requires-Dist: ipykernel; extra == 'docs'
Requires-Dist: jupytext; extra == 'docs'
Requires-Dist: matplotlib; extra == 'docs'
Requires-Dist: myst-nb; extra == 'docs'
Requires-Dist: myst-parser; extra == 'docs'
Requires-Dist: nbsphinx; extra == 'docs'
Requires-Dist: pooch; extra == 'docs'
Requires-Dist: sphinx; extra == 'docs'
Requires-Dist: sphinx-autoapi; extra == 'docs'
Requires-Dist: sphinx-autodoc-typehints; extra == 'docs'
Requires-Dist: sphinx-click; extra == 'docs'
Requires-Dist: sphinx-rtd-theme; extra == 'docs'
Provides-Extra: examples
Requires-Dist: ipykernel; extra == 'examples'
Requires-Dist: ipython; extra == 'examples'
Requires-Dist: jupyter; extra == 'examples'
Provides-Extra: pretrained
Requires-Dist: cellmap-models; extra == 'pretrained'
Requires-Dist: empanada-napari; extra == 'pretrained'
Requires-Dist: pyqt5; extra == 'pretrained'
Provides-Extra: test
Requires-Dist: pytest; extra == 'test'
Requires-Dist: pytest-cov; extra == 'test'
Requires-Dist: pytest-lazy-fixtures; extra == 'test'
